polygonal_packit/__init__.py
polygonal_packit/alpha_zero_general/Game.py
polygonal_packit/alpha_zero_general/NeuralNet.py
polygonal_packit/alpha_zero_general/PackitAIPlayer.py
polygonal_packit/alpha_zero_general/PackitArena.py
polygonal_packit/alpha_zero_general/PackitCoach.py
polygonal_packit/alpha_zero_general/PackitMCTS.py
polygonal_packit/alpha_zero_general/PackitNNetWrapper.py
polygonal_packit/alpha_zero_general/PackitTrainer.py
polygonal_packit/alpha_zero_general/RandomPlayer.py
polygonal_packit/alpha_zero_general/TestingFunctions.py
polygonal_packit/alpha_zero_general/__init__.py
polygonal_packit/alpha_zero_general/negamaxPlayer.py
polygonal_packit/alpha_zero_general/utils.py
polygonal_packit/alpha_zero_general/HexGame/HexGame.py
polygonal_packit/alpha_zero_general/HexGame/HexPlayers.py
polygonal_packit/alpha_zero_general/HexGame/__init__.py
polygonal_packit/alpha_zero_general/HexGame/keras/HexNNet.py
polygonal_packit/alpha_zero_general/HexGame/keras/HexNNetSmall.py
polygonal_packit/alpha_zero_general/HexGame/keras/NNet.py
polygonal_packit/alpha_zero_general/HexGame/keras/NNetSmall.py
polygonal_packit/alpha_zero_general/HexGame/keras/__init__.py
polygonal_packit/alpha_zero_general/HexGame/pytorch/HexNNet.py
polygonal_packit/alpha_zero_general/HexGame/pytorch/HexNNetSmall.py
polygonal_packit/alpha_zero_general/HexGame/pytorch/NNet.py
polygonal_packit/alpha_zero_general/HexGame/pytorch/__init__.py
polygonal_packit/alpha_zero_general/TriangleGame/TriangleGame.py
polygonal_packit/alpha_zero_general/TriangleGame/TrianglePlayers.py
polygonal_packit/alpha_zero_general/TriangleGame/__init__.py
polygonal_packit/alpha_zero_general/TriangleGame/keras/NNet.py
polygonal_packit/alpha_zero_general/TriangleGame/keras/NNetSmall.py
polygonal_packit/alpha_zero_general/TriangleGame/keras/TriangleNNet.py
polygonal_packit/alpha_zero_general/TriangleGame/keras/TriangleNNetSmall.py
polygonal_packit/alpha_zero_general/TriangleGame/keras/__init__.py
polygonal_packit-0.2.5.dist-info/LICENSE
polygonal_packit-0.2.5.dist-info/METADATA
polygonal_packit-0.2.5.dist-info/WHEEL
polygonal_packit-0.2.5.dist-info/top_level.txt
polygonal_packit-0.2.5.dist-info/RECORD
