Metadata-Version: 2.1
Name: polygonal-packit
Version: 0.2.5
Summary: Hexagonal and triangular version of game Pack It! along with Alpha Zero General-based RL algorithms.
Home-page: https://github.com/matejczukm/alpha-zero-general
Author: Michał Matejczuk, Piotr Kosakowski
License: MIT
Classifier: Programming Language :: Python :: 3
Classifier: License :: OSI Approved :: MIT License
Classifier: Operating System :: OS Independent
Requires-Python: >=3.8
License-File: LICENSE
Requires-Dist: numpy
Requires-Dist: torch
Requires-Dist: tqdm
Requires-Dist: huggingface-hub
Requires-Dist: tensorflow
Requires-Dist: coloredlogs
Requires-Dist: easyAI
